{"authorDailyContributionsMap":{"sianloh":[{"date":"2021-08-24","commitResults":[{"hash":"25a09cf7d1100723055251dc45deccd0e2177528","messageTitle":"level-1","messageBody":"","fileTypesAndContributionMap":{"java":{"insertions":26,"deletions":0}}},{"hash":"34072cb3d289e4955da7b2cf18959babe016fcab","messageTitle":"Level-2","messageBody":"","fileTypesAndContributionMap":{"java":{"insertions":15,"deletions":6}}}]},{"date":"2021-09-07","commitResults":[{"hash":"c32a0861e72d7b6d32b1370edc505823367e2ed0","messageTitle":"level-3","messageBody":"","fileTypesAndContributionMap":{"java":{"insertions":43,"deletions":5}}},{"hash":"2a389bf311d9826e663461248d48b7ea6869ef90","messageTitle":"level-4","messageBody":"","fileTypesAndContributionMap":{"java":{"insertions":122,"deletions":32}}}]},{"date":"2021-11-13","commitResults":[{"hash":"3ac81969c5b92a501597a9fd4e7c8ddb65885958","messageTitle":"Level-5","messageBody":"","fileTypesAndContributionMap":{"java":{"insertions":84,"deletions":67}}}]},{"date":"2021-11-14","commitResults":[{"hash":"9fb69525c3fc1d09732a3c2bbccc5cc9020bf146","messageTitle":"Level - 6","messageBody":"","fileTypesAndContributionMap":{"java":{"insertions":119,"deletions":31}}},{"hash":"afaabe7395fd2fecdf89b07b863ac1420d1af2c9","messageTitle":"Level 7, More OOP, A-Packages","messageBody":"","fileTypesAndContributionMap":{"java":{"insertions":505,"deletions":207},"bat":{"insertions":1,"deletions":1},"md":{"insertions":2,"deletions":2}}},{"hash":"a7d1083432f1d729951c1b48b5c6eba37fba4386","messageTitle":"Cleaning up codes.","messageBody":"","fileTypesAndContributionMap":{"java":{"insertions":3,"deletions":36}}},{"hash":"ce07b14044e4495e7979ab1a6686989503e4fa2d","messageTitle":"Minor updates.","messageBody":"","fileTypesAndContributionMap":{"java":{"insertions":63,"deletions":52}}},{"hash":"d4f8df552a091da804710fb883c27c1749124c3d","messageTitle":"A-JavaDoc","messageBody":"","fileTypesAndContributionMap":{"java":{"insertions":27,"deletions":7}}}]}]},"authorFileTypeContributionMap":{"sianloh":{"java":574,"md":2,"fxml":0,"sh":0,"bat":1,"gradle":0,"txt":0}},"authorContributionVariance":{"sianloh":11829.774},"authorDisplayNameMap":{"sianloh":"TAY ..BOON"}}
