{"authorDailyContributionsMap":{"ngkeiyeung":[{"date":"2021-09-21","commitResults":[{"hash":"199ee7493073c2aa0657a8e1966a6b25aa989840","messageTitle":"Level 1 Greet, Echo and Text","messageBody":"","fileTypesAndContributionMap":{"java":{"insertions":23,"deletions":0}}},{"hash":"6f54e6e0f83fa123c37b049e80ee8a646a8826ef","messageTitle":"Level 1 Updated","messageBody":"","fileTypesAndContributionMap":{"java":{"insertions":2,"deletions":1}}}]},{"date":"2021-09-22","commitResults":[{"hash":"9bd85a409329e6efe3e8bd24f2bf279f4a170e32","messageTitle":"Add level 2 - AddList","messageBody":"","fileTypesAndContributionMap":{"java":{"insertions":3,"deletions":0}}}]}]},"authorFileTypeContributionMap":{"ngkeiyeung":{"java":27,"md":0,"fxml":0,"sh":0,"bat":0,"gradle":0,"txt":0}},"authorContributionVariance":{"ngkeiyeung":14.806914},"authorDisplayNameMap":{"ngkeiyeung":"WU Q..YANG"}}
